{
  "contacts": [
    {
      "id": "1",
      "info": {
        "name": "Jason",
        "address": "Bien Hoa",
        "phone": "09891110991"
      }
    },
    {
      "id": "2",
      "info": {
        "name": "Lucky",
        "address": "HCM City",
        "phone": "0796841341"
      }
    },
    {
      "info": {
        "name": "Neo",
        "address": "Phú Quốc",
        "phone": "0358584581"
      },
      "id": "fDcau89"
    },
    {
      "info": {
        "name": "Đỗ Thị Lương",
        "address": "Biên Hòa - Đồng Nai",
        "phone": "0944405979"
      },
      "id": "vUNS0y3"
    },
    {
      "info": {
        "name": "Lã Xuân Phóng",
        "address": "620/22 Đồng Khởi",
        "phone": "0936039728"
      },
      "id": "W-v0EXo"
    }
  ]
}